img2ico/__init__.py
img2ico/__main__.py
img2ico/logging/__init__.py
img2ico/logging/_logging.py
img2ico/utils/__init__.py
img2ico/utils/_utils.py
img2ico-0.1.0.dist-info/licenses/LICENSE
img2ico-0.1.0.dist-info/METADATA
img2ico-0.1.0.dist-info/WHEEL
img2ico-0.1.0.dist-info/entry_points.txt
img2ico-0.1.0.dist-info/top_level.txt
img2ico-0.1.0.dist-info/RECORD
