Metadata-Version: 2.4
Name: img2ico
Version: 0.1.0
Summary: img2ico provides an easy way to generate favicon .ico files from various image formats.
Author: yu9824
Maintainer: yu9824
License: MIT License
Project-URL: Homepage, https://github.com/yu9824/img2ico
Project-URL: Documentation, https://yu9824.github.io/img2ico/
Project-URL: PyPI, https://pypi.org/project/img2ico/
Project-URL: Source, https://github.com/yu9824/img2ico
Project-URL: Tracker, https://github.com/yu9824/img2ico/issues
Project-URL: Changelog, https://github.com/yu9824/img2ico/blob/main/CHANGELOG.md
Keywords: icon
Classifier: Programming Language :: Python :: 3
Classifier: Programming Language :: Python :: 3.8
Classifier: Programming Language :: Python :: 3.9
Classifier: Programming Language :: Python :: 3.10
Classifier: Programming Language :: Python :: 3.11
Classifier: Programming Language :: Python :: 3.12
Classifier: Programming Language :: Python :: 3.13
Classifier: License :: OSI Approved :: MIT License
Requires-Python: >=3.8
License-File: LICENSE
Requires-Dist: pillow>=10.0.0
Provides-Extra: test
Requires-Dist: pytest; extra == "test"
Provides-Extra: dev
Requires-Dist: build; extra == "dev"
Provides-Extra: svg
Requires-Dist: cairosvg>=2.7.0; extra == "svg"
Provides-Extra: optional
Requires-Dist: colorlog; extra == "optional"
Requires-Dist: tqdm; extra == "optional"
Provides-Extra: docs
Requires-Dist: sphinx; extra == "docs"
Requires-Dist: sphinx_rtd_theme; extra == "docs"
Requires-Dist: sphinx-markdown-tables; extra == "docs"
Requires-Dist: recommonmark; extra == "docs"
Provides-Extra: gui
Requires-Dist: TkEasyGUI; extra == "gui"
Dynamic: license-file
